{
  "logoSource": "/images/logo.svg",
  "logoAlt": "Logo",
  "navData": [
    {
      "name": "Home",
      "path": "/",
      "children": []
    },
    {
      "name": "Why",
      "path": "/why/",
      "children": []
    },
    {
      "name": "Blog",
      "path": "/blog/",
      "children": []
    }
  ],
  "buttonSections": [
    {
      "_component": "building-blocks/core-elements/button",
      "text": "Search",
      "hideText": true,
      "link": "/search/",
      "iconName": "magnifying-glass",
      "iconPosition": "before",
      "variant": "ghost",
      "size": "lg"
    }
  ]
}
